lean4url/__init__.py
lean4url/constants.py
lean4url/core.py
lean4url/url_utils.py
lean4url-0.1.0.dist-info/licenses/LICENSE
lean4url-0.1.0.dist-info/METADATA
lean4url-0.1.0.dist-info/WHEEL
lean4url-0.1.0.dist-info/top_level.txt
lean4url-0.1.0.dist-info/RECORD
