Metadata-Version: 2.4
Name: lean4url
Version: 0.1.0
Summary: High-performance lzstring compression library compatible with JavaScript implementation
Home-page: https://github.com/rexwzh/lean4url
Author: Rex Wang
Author-email: 1073853456@qq.com
Project-URL: Bug Reports, https://github.com/rexwzh/lean4url/issues
Project-URL: Source, https://github.com/rexwzh/lean4url
Classifier: Development Status :: 4 - Beta
Classifier: Intended Audience :: Developers
Classifier: License :: OSI Approved :: MIT License
Classifier: Operating System :: OS Independent
Classifier: Programming Language :: Python :: 3
Classifier: Programming Language :: Python :: 3.8
Classifier: Programming Language :: Python :: 3.9
Classifier: Programming Language :: Python :: 3.10
Classifier: Programming Language :: Python :: 3.11
Classifier: Programming Language :: Python :: 3.12
Classifier: Topic :: Software Development :: Libraries :: Python Modules
Classifier: Topic :: System :: Archiving :: Compression
Requires-Python: >=3.8
License-File: LICENSE
Provides-Extra: dev
Requires-Dist: pytest>=7.0.0; extra == "dev"
Requires-Dist: pytest-cov>=4.0.0; extra == "dev"
Requires-Dist: black>=22.0.0; extra == "dev"
Requires-Dist: isort>=5.0.0; extra == "dev"
Requires-Dist: flake8>=5.0.0; extra == "dev"
Requires-Dist: mypy>=1.0.0; extra == "dev"
Requires-Dist: requests>=2.28.0; extra == "dev"
Requires-Dist: mkdocs>=1.4.0; extra == "dev"
Requires-Dist: mkdocs-material>=9.0.0; extra == "dev"
Requires-Dist: mkdocs-static-i18n>=0.5.0; extra == "dev"
Dynamic: license-file
